downsonic/__init__.py
downsonic/main.py
downsonic-0.0.3.dist-info/METADATA
downsonic-0.0.3.dist-info/WHEEL
downsonic-0.0.3.dist-info/entry_points.txt
downsonic-0.0.3.dist-info/licenses/LICENSE.md
downsonic-0.0.3.dist-info/RECORD
