Metadata-Version: 2.4
Name: downsonic
Version: 0.0.3
Summary: a little command-line utility made to help download all of a user's music from an OpenSubsonic server
Project-URL: Homepage, https://github.com/pypa/sampleproject
Project-URL: Issues, https://github.com/pypa/sampleproject/issues
Author-email: andrew sòlanto <person@dandelion.computer>
License-Expression: GPL-3.0-or-later
License-File: LICENSE.md
Classifier: Operating System :: OS Independent
Classifier: Programming Language :: Python :: 3
Requires-Python: >=3.13.9
Requires-Dist: argcomplete==3.6.3
Requires-Dist: py-opensonic==7.0.2
Requires-Dist: python-magic==0.4.27
Requires-Dist: tqdm==4.67.1
